shiny_validate/__init__.py
shiny_validate/check/__init__.py
shiny_validate/check/_check.py
shiny_validate/deps.py
shiny_validate/distjs/index.js
shiny_validate/examples/1-simple/README.md
shiny_validate/examples/1-simple/app.py
shiny_validate/examples/2-deffered/README.md
shiny_validate/examples/2-deffered/app.py
shiny_validate/examples/3-module-1/README.md
shiny_validate/examples/3-module-1/app.py
shiny_validate/examples/4-module-2/README.md
shiny_validate/examples/4-module-2/app.py
shiny_validate/examples/5-module-3/README.md
shiny_validate/examples/5-module-3/app.py
shiny_validate/examples/basic/app.py
shiny_validate/tests/3-floats-ints/app.py
shiny_validate/validator.py
shiny_validate-0.1.3.dist-info/LICENSE.md
shiny_validate-0.1.3.dist-info/METADATA
shiny_validate-0.1.3.dist-info/WHEEL
shiny_validate-0.1.3.dist-info/RECORD
