Metadata-Version: 2.3
Name: shiny_validate
Version: 0.1.3
Summary: Input Validation for Shiny apps
Author: Gordon Shotwell
Author-email: gordon.shotwell@posit.co
Requires-Python: >=3.8,<4.0
Classifier: Programming Language :: Python :: 3
Classifier: Programming Language :: Python :: 3.8
Classifier: Programming Language :: Python :: 3.9
Classifier: Programming Language :: Python :: 3.10
Classifier: Programming Language :: Python :: 3.11
Classifier: Programming Language :: Python :: 3.12
Classifier: Programming Language :: Python :: 3.13
Requires-Dist: shiny (>=0.6)
